agl_predict_endo_frame/__init__.py
agl_predict_endo_frame/inference_dataset.py
agl_predict_endo_frame/model_loader.py
agl_predict_endo_frame/postprocess.py
agl_predict_endo_frame/predict.py
agl_predict_endo_frame/prediction_visualizer.py
agl_predict_endo_frame/preprocess.py
agl_predict_endo_frame/run_visualizer.py
agl_predict_endo_frame-0.2.7.dist-info/LICENSE
agl_predict_endo_frame-0.2.7.dist-info/METADATA
agl_predict_endo_frame-0.2.7.dist-info/WHEEL
agl_predict_endo_frame-0.2.7.dist-info/entry_points.txt
agl_predict_endo_frame-0.2.7.dist-info/RECORD
